gpfit/__init__.py
gpfit/classes.py
gpfit/constraint_set.py
gpfit/fit.py
gpfit/maths/__init__.py
gpfit/maths/initialize.py
gpfit/maths/least_squares.py
gpfit/maths/logsumexp.py
gpfit/tests/__init__.py
gpfit/tests/run_tests.py
gpfit/tests/test_constraint_set.py
gpfit/tests/test_evaluate.py
gpfit/tests/test_examples.py
gpfit/tests/test_fit.py
gpfit/tests/test_initialize.py
gpfit/tests/test_least_squares.py
gpfit/tests/test_logsumexp.py
gpfit/tests/test_plot_fit.py
gpfit/tests/test_print_fit.py
gpfit/tests/baseline/isma_1d.png
gpfit/tests/baseline/isma_2d_slices.png
gpfit/tests/baseline/isma_2d_surface.png
gpfit/tests/baseline/ma_1d.png
gpfit/tests/baseline/ma_2d_slices.png
gpfit/tests/baseline/ma_2d_surface.png
gpfit/tests/baseline/sma_1d.png
gpfit/tests/baseline/sma_2d_slices.png
gpfit/tests/baseline/sma_2d_surface.png
gpfit/xfoil/__init__.py
gpfit/xfoil/constraint_set.py
gpfit/xfoil/wrapper.py
gpfit-0.2.0.dist-info/LICENSE
gpfit-0.2.0.dist-info/METADATA
gpfit-0.2.0.dist-info/WHEEL
gpfit-0.2.0.dist-info/top_level.txt
gpfit-0.2.0.dist-info/RECORD
