Metadata-Version: 2.1
Name: gpfit
Version: 0.2.0
Summary: Package for fitting geometric programming models to data
Home-page: https://github.com/convexengineering/gpfit
Author: Convex Engineering Group
Author-email: gpkit@mit.edu
License: The MIT License (MIT)        
Platform: UNKNOWN
Requires-Python: >=3.4
License-File: LICENSE
Requires-Dist: numpy
Requires-Dist: scipy
Requires-Dist: gpkit
Requires-Dist: matplotlib (>=3.3.2)
Requires-Dist: pytest (>=6.2.5)
Requires-Dist: pytest-mpl (>=0.13)
